nenucal/__init__.py
nenucal/cal.py
nenucal/cal_config/LBAdefault_after_di.rfis
nenucal/cal_config/dppp_applycal.parset
nenucal/cal_config/dppp_applycal_diag.parset
nenucal/cal_config/dppp_ddecal.parset
nenucal/cal_config/dppp_flagger.parset
nenucal/cal_config/dppp_predict.parset
nenucal/cal_config/dppp_predict_diag.parset
nenucal/cal_config/dppp_predict_nocal.parset
nenucal/cal_config/dppp_preflag.parset
nenucal/cal_config/dppp_subtract.parset
nenucal/cal_config/dppp_subtract_diag.parset
nenucal/cal_config/dppp_subtract_nocal.parset
nenucal/datahandler.py
nenucal/delayflag.py
nenucal/flagutils.py
nenucal/msutils.py
nenucal/settings.py
nenucal/skymodel.py
nenucal/smoothsol.py
nenucal/tasks.py
nenucal/templates/Ateam_lowres.skymodel
nenucal/templates/default_img_settings.toml
nenucal/templates/default_settings.toml
nenucal/templates/default_vis_flagger_config.toml
nenucal/templates/ssins_config.toml
nenucal/tests/__init__.py
nenucal/tests/test_msutils.py
nenucal/tests/test_utils.py
nenucal/tools/__init__.py
nenucal/tools/bpcal.py
nenucal/tools/calpipe.py
nenucal/tools/flagtool.py
nenucal/tools/imgpipe.py
nenucal/tools/modeltool.py
nenucal/tools/mstool.py
nenucal/tools/nenudata.py
nenucal/tools/soltool.py
nenucal/utils.py
nenucal-0.10.dist-info/LICENSE
nenucal-0.10.dist-info/METADATA
nenucal-0.10.dist-info/WHEEL
nenucal-0.10.dist-info/entry_points.txt
nenucal-0.10.dist-info/RECORD
