Metadata-Version: 2.3
Name: nenucal
Version: 0.10
Summary: Calibration pipeline for the NenuFAR Cosmic Dawn project
License: GPL-3.0-or-later
Author: Florent Mertens
Author-email: florent.mertens@gmail.com
Requires-Python: >=3.10,<4.0
Classifier: License :: OSI Approved :: GNU General Public License v3 or later (GPLv3+)
Classifier: Programming Language :: Python :: 3
Classifier: Programming Language :: Python :: 3.10
Classifier: Programming Language :: Python :: 3.11
Classifier: Programming Language :: Python :: 3.12
Classifier: Programming Language :: Python :: 3.13
Requires-Dist: astropy (>=6.0)
Requires-Dist: astroquery (>=0.4)
Requires-Dist: click (>=8.0)
Requires-Dist: libpipe (>=0.2)
Requires-Dist: losoto (>=2.3)
Requires-Dist: lsmtool (>=1.4.2)
Requires-Dist: matplotlib (>=3.0)
Requires-Dist: nenupy (>=2.0)
Requires-Dist: python-casacore (>=3.0)
Requires-Dist: requests (>=2.0)
Requires-Dist: scipy (>=1.8)
Requires-Dist: tables (>=3.2)
Requires-Dist: tabulate (>=0.8)
Requires-Dist: toml (>=0.10)
